{"https://www.instagram.com/p/CU4iQZZMbdg/": null, "https://www.instagram.com/p/CUpt_dMMcXu/": null, "https://www.instagram.com/p/CX1UDwnMWc6/": null, "https://www.instagram.com/p/CXOrwdEMHoa/": null, "https://www.instagram.com/p/CQOiixUHjQr/": null, "https://www.instagram.com/p/CS4fLoLMnE2/": null, "https://www.instagram.com/p/CX04NuKs6Uk/": null, "https://www.instagram.com/p/COvMLLpn5pI/": null, "https://www.instagram.com/p/CVS-54DMY1_/": null, "https://www.instagram.com/p/CSMgQgiMreY/": null, "https://www.instagram.com/p/CXLsFCPjbSn/": null, "https://www.instagram.com/p/CSwErICjY1K/": null, "https://www.instagram.com/p/CTEPwCDsSq7/": null, "https://www.instagram.com/p/CQiZabVHoYJ/": null, "https://www.instagram.com/p/CQDwp0_IeCD/": null, "https://www.instagram.com/p/CWYt78xj6jv/": null, "https://www.instagram.com/p/CVVjEPsDP9x/": null, "https://www.instagram.com/p/CWBNl0dsE22/": null, "https://www.instagram.com/p/CVF__6wMv1R/": null, "https://www.instagram.com/p/CTKKypMjrkG/": null, "https://www.instagram.com/p/CSR50AbMAvF/": null, "https://www.instagram.com/p/COf1sXcnyyI/": null, "https://www.instagram.com/p/COfMhUGnFjR/": null, "https://www.instagram.com/p/CYTzPM8MaoX/": null, "https://www.instagram.com/p/CQf3vjKHh_m/": null, "https://www.instagram.com/p/CRv9ajeItg3/": null, "https://www.instagram.com/p/CW0L5PFIwuk/": null, "https://www.instagram.com/p/CTAa6UcMTRt/": null, "https://www.instagram.com/p/CUiabMZMcdV/": null, "https://www.instagram.com/p/CV-ATuRoT1w/": null, "https://www.instagram.com/p/CRWz2JZMx0i/": null, "https://www.instagram.com/p/CVvTSiUMAFd/": null, "https://www.instagram.com/p/CXWTP5oMHqJ/": null, "https://www.instagram.com/p/CYjO1djMfFl/": null, "https://www.instagram.com/p/CQBPUn-rYcr/": null, "https://www.instagram.com/p/CT_ui7lIFG8/": null, "https://www.instagram.com/p/CT1pDnos7nU/": null, "https://www.instagram.com/p/CUKBscPj09E/": null, "https://www.instagram.com/p/CUU-fZ9sCcM/": null, "https://www.instagram.com/p/CXgYhTisoB_/": null, "https://www.instagram.com/p/COqYF8OKIYE/": null, "https://www.instagram.com/p/CXJa7Vtso5M/": null, "https://www.instagram.com/p/CWLdz-ispLs/": null, "https://www.instagram.com/p/CWQB1vUI_Az/": null, "https://www.instagram.com/p/CUe8Sn6M_r_/": null, "https://www.instagram.com/p/CQ6Gg_oo61Y/": null, "https://www.instagram.com/p/CR4Ob3vK6Nt/": null, "https://www.instagram.com/p/CUclbiQsezP/": null, "https://www.instagram.com/p/CXEDyYnsf_W/": null, "https://www.instagram.com/p/CQqGPxaHlUK/": null, "https://www.instagram.com/p/CQ9BmkbMm9a/": null, "https://www.instagram.com/p/CSUHeeGIznP/": null, "https://www.instagram.com/p/CS1bkb8sZJn/": null, "https://www.instagram.com/p/CS6MvKtD91X/": null, "https://www.instagram.com/p/CUZ880WsV53/": null, "https://www.instagram.com/p/CPidUXZKcq3/": null, "https://www.instagram.com/p/CSO94PYsjFv/": null, "https://www.instagram.com/p/CReCzWRouMn/": null, "https://www.instagram.com/p/CVpttxejAUc/": null, "https://www.instagram.com/p/CO7bXwbnI-F/": null, "https://www.instagram.com/p/CRrPiPtsGCj/": null, "https://www.instagram.com/p/CPBa7dTnZDz/": null, "https://www.instagram.com/p/CP5TPZPqTXq/": null, "https://www.instagram.com/p/CQnmqFMn0Bq/": null, "https://www.instagram.com/p/CSrZldLDyEL/": null, "https://www.instagram.com/p/CPQbAoEK7zZ/": null, "https://www.instagram.com/p/CTCd6mxjNRX/": null, "https://www.instagram.com/p/CVxWLDTsXWU/": null, "https://www.instagram.com/p/CSluIqysJ17/": null, "https://www.instagram.com/p/CO8Ckg0qi-N/": null, "https://www.instagram.com/p/CVIBwloMME-/": null, "https://www.instagram.com/p/CWGX_Jkjv2l/": null, "https://www.instagram.com/p/CPODxD9Hr1J/": null, "https://www.instagram.com/p/CRb-QgoMvoh/": null, "https://www.instagram.com/p/CP0SHTyrOdC/": null, "https://www.instagram.com/p/CVfjMXrsRdV/": null, "https://www.instagram.com/p/CT7jIRvMelK/": null, "https://www.instagram.com/p/CWdAirWsLAh/": null, "https://www.instagram.com/p/CUrwtMZMOwt/": null, "https://www.instagram.com/p/CPfYuMvKmnR/": null, "https://www.instagram.com/p/CUDFw3UD8tQ/": null, "https://www.instagram.com/p/CSHdT-JM-tf/": null, "https://www.instagram.com/p/CVNTJU9safI/": null, "https://www.instagram.com/p/CPLRi48nrz7/": null, "https://www.instagram.com/p/CTXmBk9sXp0/": null, "https://www.instagram.com/p/CRQ9TIDqMdm/": null, "https://www.instagram.com/p/CWq2OB3sklp/": null, "https://www.instagram.com/p/CSZiAkJDAXF/": null, "https://www.instagram.com/p/COSgyqYH_ZT/": null, "https://www.instagram.com/p/CV5DXmHDqIh/": null, "https://www.instagram.com/p/CQYrmTjnjJp/": null, "https://www.instagram.com/p/CRPQkDRsXY5/": null, "https://www.instagram.com/p/CVc2hOgsY5O/": null, "https://www.instagram.com/p/COSf8ynHGDu/": null, "https://www.instagram.com/p/CTedmR5MFvh/": null, "https://www.instagram.com/p/COdJeRTH9Es/": null, "https://www.instagram.com/p/CXYIJy9o6af/": null, "https://www.instagram.com/p/CWSfvW8D312/": null, "https://www.instagram.com/p/CXy17O4MPGK/": null, "https://www.instagram.com/p/CTharvxsT3a/": null, "https://www.instagram.com/p/CT4Rx5yMIDZ/": null, "https://www.instagram.com/p/CU-Uf-Ss9ol/": null, "https://www.instagram.com/p/CXLoR6NsSdv/": null, "https://www.instagram.com/p/CSboLbxsIKM/": null, "https://www.instagram.com/p/COw4ibVKm2i/": null, "https://www.instagram.com/p/COSguK2HCXd/": null, "https://www.instagram.com/p/CVuqOlMscrx/": null, "https://www.instagram.com/p/CUS0ztwDZsA/": null, "https://www.instagram.com/p/CXnrlAlDa07/": null, "https://www.instagram.com/p/CSOpVdzMet5/": null, "https://www.instagram.com/p/CV2LX8xsAo6/": null, "https://www.instagram.com/p/CYgqCz9FZyC/": null, "https://www.instagram.com/p/COpScymKXtn/": null, "https://www.instagram.com/p/CUU4V6DsNNB/": null, "https://www.instagram.com/p/CQX_pVLnalp/": null, "https://www.instagram.com/p/CWGQbkqs3V8/": null, "https://www.instagram.com/p/CVTP1n8DwRq/": null, "https://www.instagram.com/p/CTEu3o7sfUz/": null, "https://www.instagram.com/p/CSCaMn2j6Hg/": null, "https://www.instagram.com/p/CRbqcHTs2nB/": null, "https://www.instagram.com/p/CS4YTH-oXu9/": null, "https://www.instagram.com/p/CRoBaGTKZWm/": null, "https://www.instagram.com/p/CQNsJE9nUKY/": null, "https://www.instagram.com/p/CW8VWhqs2WN/": null, "https://www.instagram.com/p/CUxLVZHjw9N/": null, "https://www.instagram.com/p/CWlKhrmsxMa/": null, "https://www.instagram.com/p/CXiUPlFDmXe/": null, "https://www.instagram.com/p/CQF57nxNXvM/": null, "https://www.instagram.com/p/CPEDziwHX6H/": null, "https://www.instagram.com/p/CRcOWPMsPD3/": null, "https://www.instagram.com/p/CYBburusFKK/": null, "https://www.instagram.com/p/COvbU7Rnpwa/": null, "https://www.instagram.com/p/CQHMbLIs525/": null, "https://www.instagram.com/p/CVKnoFvsEl1/": null, "https://www.instagram.com/p/CTts8IyoMXB/": null, "https://www.instagram.com/p/CS1z8qxMe0H/": null, "https://www.instagram.com/p/CTjMDCrjFP6/": null, "https://www.instagram.com/p/CYbSIO_MsEj/": null, "https://www.instagram.com/p/CPtElDbrHQY/": null, "https://www.instagram.com/p/CVhqjQWDeo8/": null, "https://www.instagram.com/p/CUXAn2CjiX3/": null, "https://www.instagram.com/p/CV8WBxSsKFb/": null, "https://www.instagram.com/p/CTJ-cEdoPL7/": null, "https://www.instagram.com/p/CTgnPJDsnVi/": null, "https://www.instagram.com/p/CSG3mRvMC6M/": null, "https://www.instagram.com/p/CXtanWssA_L/": null, "https://www.instagram.com/p/CSCme6ejDuv/": null, "https://www.instagram.com/p/COSf_2EnGep/": null, "https://www.instagram.com/p/CUjxpAWIxsU/": null, "https://www.instagram.com/p/CWxmpy3sIFw/": null, "https://www.instagram.com/p/CVfbhUcsIPR/": null, "https://www.instagram.com/p/CYgG-C5MfV8/": null, "https://www.instagram.com/p/CSouUcSs0mp/": null, "https://www.instagram.com/p/CV0qlRXM0mb/": null, "https://www.instagram.com/p/CWvr-Y4s_rV/": null, "https://www.instagram.com/p/CYlfB4SM0Ux/": null, "https://www.instagram.com/p/CQns7WFIpYA/": null, "https://www.instagram.com/p/CXT1n78s5dw/": null, "https://www.instagram.com/p/CUKrDz3svic/": null, "https://www.instagram.com/p/CV2fqwKMgGJ/": null, "https://www.instagram.com/p/CQBmtayKdc9/": null, "https://www.instagram.com/p/CUMmNHbD_eo/": null, "https://www.instagram.com/p/CYn8y9bMu2r/": null, "https://www.instagram.com/p/CXqJtrYI486/": null, "https://www.instagram.com/p/CW8A790Mp-s/": null, "https://www.instagram.com/p/CVZ2XIfoaWn/": null, "https://www.instagram.com/p/CUt9_tqsiV-/": null, "https://www.instagram.com/p/CYmOthWsI2u/": null, "https://www.instagram.com/p/CX3no6KlpbI/": null}